{"experiment": {"id":  "e98873",
                "name": "Performance Evaluation of Mine Evasee Present in a Ventilation System",
                "discipline_id": "Mining Engineering",
                "institute_id": "iitkgp",
                "developers": [{"name":"dev1", "email": "dev1_id"},
                                {"name":"dev2", "email": "dev2_id"}],
                "hosting_info": [{"hosting_status": "host_status", "hosted_on": "host_on", "hosted_url": "http://vlabs.iitkgp.ernet.in/mv/exp10/index.html"},
                                 {"hosting_status": "host_status", "hosted_on": "host_on", "hosted_url": "http://vlabs.iitkgp.ernet.in/mv/exp10/index.html"}],
                "integration_level": "4",
                "assets": [{"asset_type": "Images", "path": "vlabs.ac.in/images/static/logo.png"},
                            {"asset_type": "Videos", "path": "vlabs.ac.in/video/abc.mkv"}],
                "sections" : ["THEORY", 
 							 "INSTRUMENTS", 
 							 "VIDEO DEMO", 
 							 "PROCEDURE", 
 							 "SIMULATOR PROCEDURE", 
 							 "SIMULATOR", 
 							 "REFERENCE"]
              }
}
