{
        "course": {"org": "iitr","id": "bmi", "display_name": "BioMedical Instrumentation Lab"},
        "overview": "BioMedical Instrumentation Lab",
        "experiments": [{"name": "Introduction",
                         "subsections": [{"name": "Introduction"}
                                         ]},
                         {"name": "ECG signal acquisition under incorrect electrode placement",
                         "subsections": [{"name": "THEORY"},
                                         {"name": "OBJECTIVE"},
                                         {"name": "EQUIPMENT USED"},
                                         {"name": "EXPERIMENT"},
                                         {"name": "QUIZZES"},        
                                         {"name": "PROCEDURE"},
                                         {"name": "FURTHER READINGS"},
                                         ]},
                          {"name": "ECG feature extraction and analysis",
                         "subsections": [{"name": "THEORY"},
                                         {"name": "OBJECTIVE"},
                                         {"name": "EQUIPMENT USED"},
                                         {"name": "EXPERIMENT"},
                                         {"name": "QUIZZES"},        
                                         {"name": "PROCEDURE"},
                                         {"name": "FURTHER READINGS"},
                                         ]},
                           {"name": "ECG Acquisition and HRV analysis in time and frequency domain",
                         "subsections": [{"name": "THEORY"},
                                         {"name": "OBJECTIVE"},
                                         {"name": "EQUIPMENT USED"},
                                         {"name": "EXPERIMENT"},
                                         {"name": "QUIZZES"},        
                                         {"name": "PROCEDURE"},
                                         {"name": "FURTHER READINGS"},
                                         ]},
                           {"name": "EEG acquisition and frequency components calculation",
                         "subsections": [{"name": "THEORY"},
                                         {"name": "OBJECTIVE"},
                                         {"name": "EQUIPMENT USED"},
                                         {"name": "EXPERIMENT"},
                                         {"name": "QUIZZES"},        
                                         {"name": "PROCEDURE"},
                                         {"name": "FURTHER READINGS"},
                                         ]},
                           {"name": "EEG Power Spectral Density calculation",
                         "subsections": [{"name": "THEORY"},
                                         {"name": "OBJECTIVE"},
                                         {"name": "EQUIPMENT USED"},
                                         {"name": "EXPERIMENT"},
                                         {"name": "QUIZZES"},        
                                         {"name": "PROCEDURE"},
                                         {"name": "FURTHER READINGS"},
                                         ]},
                           {"name": "EEG approximate entropty calculation",
                         "subsections": [{"name": "THEORY"},
                                         {"name": "OBJECTIVE"},
                                         {"name": "EQUIPMENT USED"},
                                         {"name": "EXPERIMENT"},
                                         {"name": "QUIZZES"},        
                                         {"name": "PROCEDURE"},
                                         {"name": "FURTHER READINGS"},
                                         ]},
                            {"name": "EEG alpha RMS derivation",
                         "subsections": [{"name": "THEORY"},
                                         {"name": "OBJECTIVE"},
                                         {"name": "EQUIPMENT USED"},
                                         {"name": "EXPERIMENT"},
                                         {"name": "QUIZZES"},        
                                         {"name": "PROCEDURE"},
                                         {"name": "FURTHER READINGS"},
                                         ]},
                            {"name": "EMG Toolbox",
                         "subsections": [{"name": "THEORY"},
                                         {"name": "OBJECTIVE"},
                                         {"name": "EQUIPMENT USED"},
                                         {"name": "EXPERIMENT"},
                                         {"name": "QUIZZES"},        
                                         {"name": "PROCEDURE"},
                                         {"name": "FURTHER READINGS"},
                                         ]}
                        ]

}

