{
        "course": {"org": "IIITH","id": "cse11", "display_name": "Computer Systems Organization Lab"},
        "overview": "Computer science is all about providing abstractions and their efficient implementation. An abstraction provides a logical view of a certain service or a resource by giving a well-defined black-box model, its associated properties and hides the internal details of the black-box. ",
        "experiments": [{"name": "Introduction",
                         "subsections": [{"name": "Introduction"},
                                         {"name": "List of experiments"},
                                         {"name": "Target Audience"},
                                         {"name": "Courses"},
                                         {"name": "Prerequisites"},
                                         {"name": "Feedback"}
                                         ]},
                         {"name": " Representation of Integers and their Arithmetic ",
                         "subsections": [{"name": "Introduction"},
                                         {"name": "Theory"},
                                         {"name": "Objective"},
                                         {"name": "Experiment"},
                                         {"name": "Manual"},        
                                         {"name": "Quizzes"},
                                         {"name": "Procedure"},
                                         {"name": "References"},
                                         {"name": "Feedback"}
                                         ]},
                          {"name": " Representation of Floating Point Numbers and their Arithmetic ",
                         "subsections": [{"name": "Introduction"},
                                         {"name": "Theory"},
                                         {"name": "Objective"},
                                         {"name": "Experiment"},
                                         {"name": "Manual"},        
                                         {"name": "Quizzes"},
                                         {"name": "Procedure"},
                                         {"name": "References"},
                                         {"name": "Feedback"}
                                         ]},
                           {"name": " Virtual Memory ",
                         "subsections": [{"name": "Introduction"},
                                         {"name": "Theory"},
                                         {"name": "Objective"},
                                         {"name": "Experiment"},
                                         {"name": "Manual"},        
                                         {"name": "Quizzes"},
                                         {"name": "Procedure"},
                                         {"name": "References"},
                                         {"name": "Feedback"}
                                         ]},
                           {"name": " MIPS Assembly Language Programming - 1 ",
                         "subsections": [{"name": "Introduction"},
                                         {"name": "Theory"},
                                         {"name": "Objective"},
                                         {"name": "Experiment"},
                                         {"name": "Manual"},        
                                         {"name": "Quizzes"},
                                         {"name": "Procedure"},
                                         {"name": "References"},
                                         {"name": "Feedback"}
                                         ]},
                           {"name": " MIPS Assembly Language Programming - 2 ",
                         "subsections": [{"name": "Introduction"},
                                         {"name": "Theory"},
                                         {"name": "Objective"},
                                         {"name": "Experiment"},
                                         {"name": "Manual"},        
                                         {"name": "Quizzes"},
                                         {"name": "Procedure"},
                                         {"name": "References"},
                                         {"name": "Feedback"}
                                         ]},
                           {"name": " ARM Assembly Language Programming - 1 ",
                         "subsections": [{"name": "Introduction"},
                                         {"name": "Theory"},
                                         {"name": "Objective"},
                                         {"name": "Experiment"},
                                         {"name": "Manual"},        
                                         {"name": "Quizzes"},
                                         {"name": "Procedure"},
                                         {"name": "Feedback"}
                                         ]},
                         {"name": " ARM Assembly Language Programming - 2 ",
                        "subsections": [{"name": "Introduction"},
                                         {"name": "Theory"},
                                         {"name": "Objective"},
                                         {"name": "Experiment"},
                                         {"name": "Manual"},        
                                         {"name": "Quizzes"},
                                         {"name": "Procedure"},
                                         {"name": "References"},
                                         {"name": "Feedback"}
                                         ]},
                          {"name": " Single Cycle MIPS CPU ",
                         "subsections": [{"name": "Introduction"},
                                         {"name": "Theory"},
                                         {"name": "Objective"},
                                         {"name": "Experiment"},
                                         {"name": "Manual"},        
                                         {"name": "Quizzes"},
                                         {"name": "Procedure"},
                                         {"name": "References"},
                                         {"name": "Feedback"}
                                         ]}
                            
                            
                        ]

}
