{"experiment": {"id":  "e99906",
	 	"name": "To study influence of process parameters on the Wire EDM",
	 	"overview": "This experiments deals with To study influence of process parameters on the Wire EDM",
	 	"sections" : ["Aim & Objective", 
 			      "Pre Test", 
 			      "Prerequisites", 
 			      "Theory", 
 			      "Experimental setup", 
 			      "Procedure", 
 			      "Simulator", 
 			      "Audio/Video", 
 			      "Post Test", 
 			      "Conclusion", 
 			      "Reference", 
 			      "Feedback"]		
		},
		"content-type": "org"
}